Metadata-Version: 2.4
Name: llama-index-llms-zhipuai
Version: 0.4.1
Summary: llama-index llms zhipuai integration
Author: nightosong
License-Expression: MIT
License-File: LICENSE
Requires-Python: <4.0,>=3.9
Requires-Dist: llama-index-core<0.15,>=0.13.0
Requires-Dist: zhipuai<3,>=2.1.5.20230904
